clot/__init__.py
clot/bencode/__init__.py
clot/bencode/decoder.py
clot/bencode/encoder.py
test/__init__.py
test/test_decoder.py
test/test_encoder.py
clot-2.0.0.dist-info/LICENSE
clot-2.0.0.dist-info/METADATA
clot-2.0.0.dist-info/WHEEL
clot-2.0.0.dist-info/top_level.txt
clot-2.0.0.dist-info/zip-safe
clot-2.0.0.dist-info/RECORD
